enviable.py
enviable-1.0.0.dist-info/LICENSE
enviable-1.0.0.dist-info/METADATA
enviable-1.0.0.dist-info/WHEEL
enviable-1.0.0.dist-info/top_level.txt
enviable-1.0.0.dist-info/RECORD
