Metadata-Version: 2.1
Name: enviable
Version: 1.0.0
Summary: Yet another wrapper object for environment variables. Does only the things I care about.
Home-page: https://github.com/kezabelle/python-enviable
Author: Keryn Knight
Author-email: python-enviable@kerynknight.com
Maintainer: Keryn Knight
Maintainer-email: python-enviable@kerynknight.com
License: BSD License
Keywords: environment variables
Platform: UNKNOWN
Classifier: Development Status :: 3 - Alpha
Classifier: Intended Audience :: Developers
Classifier: License :: OSI Approved :: BSD License
Classifier: Programming Language :: Python :: 2
Classifier: Programming Language :: Python :: 3
License-File: LICENSE
